WeiXueyuanQianrushiJiaocheng/README.md
WeiXueyuanQianrushiJiaocheng/__init__.py
WeiXueyuanQianrushiJiaocheng/__main__.py
WeiXueyuanQianrushiJiaocheng/file.epub
WeiXueyuanQianrushiJiaocheng/index.html
WeiXueyuanQianrushiJiaocheng/css/__init__.py
WeiXueyuanQianrushiJiaocheng/css/annotations.css
WeiXueyuanQianrushiJiaocheng/css/main.css
WeiXueyuanQianrushiJiaocheng/css/normalize.css
WeiXueyuanQianrushiJiaocheng/css/popup.css
WeiXueyuanQianrushiJiaocheng/font/__init__.py
WeiXueyuanQianrushiJiaocheng/font/fontello.eot
WeiXueyuanQianrushiJiaocheng/font/fontello.svg
WeiXueyuanQianrushiJiaocheng/font/fontello.ttf
WeiXueyuanQianrushiJiaocheng/font/fontello.woff
WeiXueyuanQianrushiJiaocheng/img/__init__.py
WeiXueyuanQianrushiJiaocheng/img/annotator-glyph-sprite.png
WeiXueyuanQianrushiJiaocheng/img/annotator-icon-sprite.png
WeiXueyuanQianrushiJiaocheng/img/apple-touch-icon.png
WeiXueyuanQianrushiJiaocheng/img/cancelfullscreen.png
WeiXueyuanQianrushiJiaocheng/img/close.png
WeiXueyuanQianrushiJiaocheng/img/fullscreen.png
WeiXueyuanQianrushiJiaocheng/img/loader.gif
WeiXueyuanQianrushiJiaocheng/img/menu-icon.png
WeiXueyuanQianrushiJiaocheng/img/save.png
WeiXueyuanQianrushiJiaocheng/img/saved.png
WeiXueyuanQianrushiJiaocheng/img/settings-s.png
WeiXueyuanQianrushiJiaocheng/img/settings.png
WeiXueyuanQianrushiJiaocheng/img/star.png
WeiXueyuanQianrushiJiaocheng/js/__init__.py
WeiXueyuanQianrushiJiaocheng/js/epub.js
WeiXueyuanQianrushiJiaocheng/js/epub.min.js
WeiXueyuanQianrushiJiaocheng/js/epub.min.map
WeiXueyuanQianrushiJiaocheng/js/hooks.min.js
WeiXueyuanQianrushiJiaocheng/js/hooks.min.map
WeiXueyuanQianrushiJiaocheng/js/reader.js
WeiXueyuanQianrushiJiaocheng/js/reader.js.map
WeiXueyuanQianrushiJiaocheng/js/reader.min.js
WeiXueyuanQianrushiJiaocheng/js/reader.min.map
WeiXueyuanQianrushiJiaocheng/js/hooks/__init__.py
WeiXueyuanQianrushiJiaocheng/js/hooks/extensions/__init__.py
WeiXueyuanQianrushiJiaocheng/js/hooks/extensions/highlight.js
wei_xueyuan_qianrushi_jiaocheng-2024.3.6.0.dist-info/METADATA
wei_xueyuan_qianrushi_jiaocheng-2024.3.6.0.dist-info/WHEEL
wei_xueyuan_qianrushi_jiaocheng-2024.3.6.0.dist-info/entry_points.txt
wei_xueyuan_qianrushi_jiaocheng-2024.3.6.0.dist-info/top_level.txt
wei_xueyuan_qianrushi_jiaocheng-2024.3.6.0.dist-info/RECORD
